dingtalk/__init__.py
dingtalk/client/__init__.py
dingtalk/client/base.py
dingtalk/client/channel.py
dingtalk/client/isv.py
dingtalk/client/api/__init__.py
dingtalk/client/api/attendance.py
dingtalk/client/api/base.py
dingtalk/client/api/blackboard.py
dingtalk/client/api/bpms.py
dingtalk/client/api/calendar.py
dingtalk/client/api/callback.py
dingtalk/client/api/chat.py
dingtalk/client/api/checkin.py
dingtalk/client/api/cspace.py
dingtalk/client/api/department.py
dingtalk/client/api/employeerm.py
dingtalk/client/api/ext.py
dingtalk/client/api/extcontact.py
dingtalk/client/api/health.py
dingtalk/client/api/message.py
dingtalk/client/api/microapp.py
dingtalk/client/api/report.py
dingtalk/client/api/role.py
dingtalk/client/api/taobao.py
dingtalk/client/api/user.py
dingtalk/client/api/workrecord.py
dingtalk/core/__init__.py
dingtalk/core/constants.py
dingtalk/core/exceptions.py
dingtalk/core/utils.py
dingtalk/crypto/__init__.py
dingtalk/crypto/base.py
dingtalk/crypto/cryptography.py
dingtalk/crypto/pkcs7.py
dingtalk/crypto/pycrypto.py
dingtalk/model/__init__.py
dingtalk/model/field.py
dingtalk/model/message.py
dingtalk/storage/__init__.py
dingtalk/storage/cache.py
dingtalk/storage/kvstorage.py
dingtalk/storage/memorystorage.py
dingtalk_sdk-1.3.8.dist-info/LICENSE
dingtalk_sdk-1.3.8.dist-info/METADATA
dingtalk_sdk-1.3.8.dist-info/WHEEL
dingtalk_sdk-1.3.8.dist-info/top_level.txt
dingtalk_sdk-1.3.8.dist-info/RECORD
